autostat/__init__.py
autostat/kernel_search.py
autostat/kernel_swaps.py
autostat/kernel_tree_types.py
autostat/kernel_trees_generic.py
autostat/kernel_trees_gpytorch.py
autostat/kernel_trees_sklearn.py
autostat/math.py
autostat/tests/__init__.py
autostat/tests/kernel_spec_generic_test.py
autostat/tests/kernels_sklearn_test.py
autostat/utils/__init__.py
autostat/utils/mauna_data_loader.py
autostat-0.0.2.dist-info/LICENSE
autostat-0.0.2.dist-info/METADATA
autostat-0.0.2.dist-info/WHEEL
autostat-0.0.2.dist-info/top_level.txt
autostat-0.0.2.dist-info/RECORD
