Metadata-Version: 2.1
Name: autostat
Version: 0.0.2
Summary: An implementation of the a Gaussian process kernel selection algorithm inspired by the Automatic Statistician
Home-page: https://github.com/sutoiku/autostat
Author: Brendan Colloran, Sutoiku Inc.
Author-email: brendan@stoic.com
License: MIT
Download-URL: https://pypi.org/project/autostat/
Keywords: Automatic Statistician,Gaussian Process
Platform: UNKNOWN
License-File: LICENSE
Requires-Dist: scikit-learn
Requires-Dist: matplotlib
Requires-Dist: numpy
